ayuda/__init__.py
ayuda/components.py
ayuda/config.py
ayuda/main.py
ayuda/messages.py
ayuda/messages/__init__.py
ayuda-0.12.dist-info/METADATA
ayuda-0.12.dist-info/WHEEL
ayuda-0.12.dist-info/entry_points.txt
ayuda-0.12.dist-info/top_level.txt
ayuda-0.12.dist-info/RECORD
