Metadata-Version: 2.1
Name: ayuda
Version: 0.12
Summary: Program for save your notes and share between git
Home-page: https://gitlab.com/rodrigohernan.ramos/ayuda
Author: Rodrigo Ramos
Author-email: rodrigohernan.ramos@gmail.com
License: UNKNOWN
Platform: UNKNOWN
Requires-Python: >=3.6
Requires-Dist: urwid
Requires-Dist: PyYaml
Requires-Dist: gitpython
